{
   "creator": "Yosys 0.43 (git sha1 ead4718e5, g++ 11.4.0-1ubuntu1~22.04 -fPIC -Os)",
   "invocation": "stat -json -top top -liberty /home/gaod/derui_work/assassyn-workloads/scripts/post_sythesis/build/top/job0/syn/0/inputs/sc_dff_library.lib -liberty /home/gaod/derui_work/assassyn-workloads/scripts/post_sythesis/build/top/job0/syn/0/inputs/sc_logic_asap7sc7p5t_rvt_asap7sc7p5t_AO_RVT_SS_nldm.lib -liberty /home/gaod/derui_work/assassyn-workloads/scripts/post_sythesis/build/top/job0/syn/0/inputs/sc_logic_asap7sc7p5t_rvt_asap7sc7p5t_INVBUF_RVT_SS_nldm.lib -liberty /home/gaod/derui_work/assassyn-workloads/scripts/post_sythesis/build/top/job0/syn/0/inputs/sc_logic_asap7sc7p5t_rvt_asap7sc7p5t_OA_RVT_SS_nldm.lib -liberty /home/gaod/derui_work/assassyn-workloads/scripts/post_sythesis/build/top/job0/syn/0/inputs/sc_logic_asap7sc7p5t_rvt_asap7sc7p5t_SEQ_RVT_SS_nldm.lib -liberty /home/gaod/derui_work/assassyn-workloads/scripts/post_sythesis/build/top/job0/syn/0/inputs/sc_logic_asap7sc7p5t_rvt_asap7sc7p5t_SIMPLE_RVT_SS_nldm.lib ",
   "modules": {
      "\\top": {
         "num_wires":         1213,
         "num_wire_bits":     1299,
         "num_pub_wires":     61,
         "num_pub_wire_bits": 147,
         "num_ports":         8,
         "num_port_bits":     94,
         "num_memories":      0,
         "num_memory_bits":   0,
         "num_processes":     0,
         "num_cells":         1198,
         "area":              174.857940,
         "num_cells_by_type": {
            "AND2x2_ASAP7_75t_R": 50,
            "AND3x1_ASAP7_75t_R": 1,
            "AND4x1_ASAP7_75t_R": 12,
            "AND5x1_ASAP7_75t_R": 12,
            "AO21x1_ASAP7_75t_R": 200,
            "AO221x1_ASAP7_75t_R": 9,
            "AO22x1_ASAP7_75t_R": 2,
            "AO32x1_ASAP7_75t_R": 6,
            "AOI211x1_ASAP7_75t_R": 1,
            "AOI21x1_ASAP7_75t_R": 1,
            "AOI22x1_ASAP7_75t_R": 2,
            "BUFx2_ASAP7_75t_R": 68,
            "DFFASRHQNx1_ASAP7_75t_R": 125,
            "DFFHQNx1_ASAP7_75t_R": 129,
            "FAx1_ASAP7_75t_R": 4,
            "HAxp5_ASAP7_75t_R": 17,
            "INVx1_ASAP7_75t_R": 75,
            "NAND2x1_ASAP7_75t_R": 26,
            "NOR2x1_ASAP7_75t_R": 163,
            "OA211x2_ASAP7_75t_R": 12,
            "OA21x2_ASAP7_75t_R": 68,
            "OA222x2_ASAP7_75t_R": 31,
            "OA22x2_ASAP7_75t_R": 1,
            "OA31x2_ASAP7_75t_R": 1,
            "OA33x2_ASAP7_75t_R": 1,
            "OAI21x1_ASAP7_75t_R": 54,
            "OAI22x1_ASAP7_75t_R": 3,
            "OR2x2_ASAP7_75t_R": 36,
            "OR3x1_ASAP7_75t_R": 30,
            "OR4x1_ASAP7_75t_R": 7,
            "OR5x1_ASAP7_75t_R": 16,
            "TIEHIx1_ASAP7_75t_R": 1,
            "TIELOx1_ASAP7_75t_R": 1,
            "XNOR2x1_ASAP7_75t_R": 1,
            "XNOR2x2_ASAP7_75t_R": 28,
            "XOR2x2_ASAP7_75t_R": 3,
            "memory_blackbox_array_d6227": 1
         }
      }
   },
      "design": {
         "num_wires":         1213,
         "num_wire_bits":     1299,
         "num_pub_wires":     61,
         "num_pub_wire_bits": 147,
         "num_ports":         8,
         "num_port_bits":     94,
         "num_memories":      0,
         "num_memory_bits":   0,
         "num_processes":     0,
         "num_cells":         1198,
         "area":              174.857940,
         "num_cells_by_type": {
            "AND2x2_ASAP7_75t_R": 50,
            "AND3x1_ASAP7_75t_R": 1,
            "AND4x1_ASAP7_75t_R": 12,
            "AND5x1_ASAP7_75t_R": 12,
            "AO21x1_ASAP7_75t_R": 200,
            "AO221x1_ASAP7_75t_R": 9,
            "AO22x1_ASAP7_75t_R": 2,
            "AO32x1_ASAP7_75t_R": 6,
            "AOI211x1_ASAP7_75t_R": 1,
            "AOI21x1_ASAP7_75t_R": 1,
            "AOI22x1_ASAP7_75t_R": 2,
            "BUFx2_ASAP7_75t_R": 68,
            "DFFASRHQNx1_ASAP7_75t_R": 125,
            "DFFHQNx1_ASAP7_75t_R": 129,
            "FAx1_ASAP7_75t_R": 4,
            "HAxp5_ASAP7_75t_R": 17,
            "INVx1_ASAP7_75t_R": 75,
            "NAND2x1_ASAP7_75t_R": 26,
            "NOR2x1_ASAP7_75t_R": 163,
            "OA211x2_ASAP7_75t_R": 12,
            "OA21x2_ASAP7_75t_R": 68,
            "OA222x2_ASAP7_75t_R": 31,
            "OA22x2_ASAP7_75t_R": 1,
            "OA31x2_ASAP7_75t_R": 1,
            "OA33x2_ASAP7_75t_R": 1,
            "OAI21x1_ASAP7_75t_R": 54,
            "OAI22x1_ASAP7_75t_R": 3,
            "OR2x2_ASAP7_75t_R": 36,
            "OR3x1_ASAP7_75t_R": 30,
            "OR4x1_ASAP7_75t_R": 7,
            "OR5x1_ASAP7_75t_R": 16,
            "TIEHIx1_ASAP7_75t_R": 1,
            "TIELOx1_ASAP7_75t_R": 1,
            "XNOR2x1_ASAP7_75t_R": 1,
            "XNOR2x2_ASAP7_75t_R": 28,
            "XOR2x2_ASAP7_75t_R": 3,
            "memory_blackbox_array_d6227": 1
         }
      }
}

